ruledownloader/__init__.py
ruledownloader/rulechanges.py
ruledownloader/ruledownloader.py
ruledownloader-1.0.0.dist-info/LICENSE.md
ruledownloader-1.0.0.dist-info/WHEEL
ruledownloader-1.0.0.dist-info/METADATA
ruledownloader-1.0.0.dist-info/entry_points.txt
ruledownloader-1.0.0.dist-info/RECORD
