Metadata-Version: 2.1
Name: ruledownloader
Version: 1.0.0
Summary: A tool for downloading and archiving Snort and Suricata rules
Home-page: https://github.com/paigeadelethompson/ruledownloader
License: MIT
Keywords: suricata,snort,security
Author: Jason Ish
Maintainer: Paige Thompson
Maintainer-email: paige@paige.bio
Requires-Python: >=3.8,<4.0
Classifier: License :: OSI Approved :: MIT License
Classifier: Programming Language :: Python
Classifier: Programming Language :: Python :: 3
Classifier: Programming Language :: Python :: 3.8
Classifier: Programming Language :: Python :: 3.9
Classifier: Programming Language :: Python :: 3.10
Classifier: Programming Language :: Python :: 3.11
Requires-Dist: configparser
Project-URL: Documentation, https://github.com/paigeadelethompson/ruledownloader#rule-downloader
Project-URL: Repository, https://github.com/paigeadelethompson/ruledownloader.git
